mkdocs_diagrams/__init__.py
mkdocs_diagrams/plugin.py
mkdocs_diagrams-1.0.0.dist-info/LICENSE
mkdocs_diagrams-1.0.0.dist-info/METADATA
mkdocs_diagrams-1.0.0.dist-info/WHEEL
mkdocs_diagrams-1.0.0.dist-info/entry_points.txt
mkdocs_diagrams-1.0.0.dist-info/top_level.txt
mkdocs_diagrams-1.0.0.dist-info/RECORD
