Metadata-Version: 2.1
Name: mkdocs-diagrams
Version: 1.0.0
Summary: MkDocs plugin to render Diagrams files
Home-page: https://github.com/zoni/mkdocs-diagrams
Author: Nick Groenen
Author-email: nick@groenen.me
License: MIT
Platform: UNKNOWN
Classifier: Development Status :: 5 - Production/Stable
Classifier: License :: OSI Approved :: MIT License
Classifier: Operating System :: OS Independent
Classifier: Programming Language :: Python :: 3
Requires-Dist: mkdocs
Requires-Dist: diagrams
